{
	"Ten": "ZTE Blade D Lux 16GB",
	"Ma_so": "ANDROID_23",
	"Don_gia_Ban": 7920000,
	"Don_gia_Nhap": 6920000,
	"Nhom_Dien_thoai": {
		"Ten": "Android",
		"Ma_so": "ANDROID"
	},
	"Danh_sach_Phieu_Dat": [
		{
			"Ngay_Dat_hang": "2018-06-19T11:09:00.540Z",
			"Ngay_Giao_hang": "2018-06-19T11:09:00.540Z",
			"So_luong": 1,
			"Don_gia_Ban": 7920000,
			"Tien": 7920000,
			"Trang_thai": "CHUA_GIAO_HANG",
			"Khach_hang": {
				"Ho_ten": "Trí",
				"Dien_thoai": "0978 111222",
				"Email": "tri@gmail.com",
				"Dia_chi": "227 Nguyễn Văn Cừ"
			},
			"So_Phieu_Dat": 1
		}
	],
	"Danh_sach_Phieu_Ban": [],
	"Danh_sach_Phieu_Nhap": [
		{
			"Ngay": "2018-04-20T02:52:11.072Z",
			"So_luong": 10,
			"Don_gia": 6920000,
			"Tien": 69200000,
			"Nhan_vien": {
				"Ho_Ten": "Trần Tiến Quang",
				"Ma_so": "NV_2"
			},
			"So_Phieu_Nhap": 1
		}
	]
}